{
    "layoutName": "默认表单布局",
    "entityCode": 1968,
    "layoutJson": "{\"widgetList\":[{\"key\":90905,\"type\":\"card\",\"category\":\"container\",\"icon\":\"card\",\"widgetList\":[{\"key\":51584,\"type\":\"grid\",\"alias\":\"column-2-grid\",\"category\":\"container\",\"icon\":\"column-2-grid\",\"cols\":[{\"type\":\"grid-col\",\"category\":\"container\",\"icon\":\"grid-col\",\"internal\":true,\"widgetList\":[{\"type\":\"reference\",\"alias\":\"\",\"icon\":\"reference-field\",\"formItemFlag\":true,\"options\":{\"name\":\"gongyingshangmingcheng\",\"keyNameEnabled\":false,\"keyName\":\"\",\"label\":\"供应商名称\",\"labelAlign\":\"\",\"placeholder\":\"\",\"columnWidth\":\"200px\",\"size\":\"\",\"labelWidth\":null,\"labelHidden\":false,\"labelWrap\":false,\"disabled\":false,\"hidden\":false,\"required\":false,\"requiredHint\":\"\",\"validation\":\"\",\"validationHint\":\"\",\"newTest\":\"\",\"customClass\":[],\"labelIconClass\":null,\"labelIconPosition\":\"rear\",\"labelTooltip\":null,\"prefixIcon\":\"\",\"suffixIcon\":\"\",\"buttonIcon\":\"Search\",\"onCreated\":\"\",\"onMounted\":\"\",\"onChange\":\"\",\"onValidate\":\"\",\"onRecordSelected\":\"\"},\"nameReadonly\":true,\"id\":\"reference80295\"}],\"options\":{\"name\":\"gridCol91372\",\"hidden\":false,\"span\":12,\"offset\":0,\"push\":0,\"pull\":0,\"responsive\":false,\"md\":12,\"sm\":12,\"xs\":12,\"customClass\":\"\"},\"id\":\"grid-col-91372\"},{\"type\":\"grid-col\",\"category\":\"container\",\"icon\":\"grid-col\",\"internal\":true,\"widgetList\":[{\"type\":\"reference\",\"alias\":\"\",\"icon\":\"reference-field\",\"formItemFlag\":true,\"options\":{\"name\":\"xunjiafaqiren\",\"keyNameEnabled\":false,\"keyName\":\"\",\"label\":\"询价发起人\",\"labelAlign\":\"\",\"placeholder\":\"\",\"columnWidth\":\"200px\",\"size\":\"\",\"labelWidth\":null,\"labelHidden\":false,\"labelWrap\":false,\"disabled\":false,\"hidden\":false,\"required\":false,\"requiredHint\":\"\",\"validation\":\"\",\"validationHint\":\"\",\"newTest\":\"\",\"customClass\":\"\",\"labelIconClass\":null,\"labelIconPosition\":\"rear\",\"labelTooltip\":null,\"prefixIcon\":\"\",\"suffixIcon\":\"\",\"buttonIcon\":\"Search\",\"onCreated\":\"\",\"onMounted\":\"\",\"onChange\":\"\",\"onValidate\":\"\",\"onRecordSelected\":\"\"},\"nameReadonly\":true,\"id\":\"reference99023\"}],\"options\":{\"name\":\"gridCol90040\",\"hidden\":false,\"span\":12,\"offset\":0,\"push\":0,\"pull\":0,\"responsive\":false,\"md\":12,\"sm\":12,\"xs\":12,\"customClass\":\"\"},\"id\":\"grid-col-90040\"},{\"type\":\"grid-col\",\"category\":\"container\",\"icon\":\"grid-col\",\"internal\":true,\"widgetList\":[{\"type\":\"date\",\"icon\":\"date-field\",\"formItemFlag\":true,\"options\":{\"name\":\"xunjiakaishiriqi\",\"keyNameEnabled\":false,\"keyName\":\"\",\"label\":\"询价开始日期\",\"labelAlign\":\"\",\"type\":\"date\",\"defaultValue\":null,\"placeholder\":\"\",\"columnWidth\":\"200px\",\"size\":\"\",\"autoFullWidth\":true,\"labelWidth\":null,\"labelHidden\":false,\"labelWrap\":false,\"readonly\":false,\"disabled\":false,\"hidden\":false,\"clearable\":true,\"editable\":false,\"format\":\"YYYY-MM-DD\",\"valueFormat\":\"YYYY-MM-DD\",\"required\":false,\"requiredHint\":\"\",\"validation\":\"\",\"validationHint\":\"\",\"customClass\":\"\",\"labelIconClass\":null,\"labelIconPosition\":\"rear\",\"labelTooltip\":null,\"onCreated\":\"\",\"onMounted\":\"\",\"onChange\":\"\",\"onFocus\":\"\",\"onBlur\":\"\",\"onValidate\":\"\"},\"nameReadonly\":true,\"id\":\"date67343\"}],\"options\":{\"name\":\"gridCol97052\",\"hidden\":false,\"span\":12,\"offset\":0,\"push\":0,\"pull\":0,\"responsive\":false,\"md\":12,\"sm\":12,\"xs\":12,\"customClass\":\"\"},\"id\":\"grid-col-97052\"},{\"type\":\"grid-col\",\"category\":\"container\",\"icon\":\"grid-col\",\"internal\":true,\"widgetList\":[{\"type\":\"date\",\"icon\":\"date-field\",\"formItemFlag\":true,\"options\":{\"name\":\"baojiajiezhiriqi\",\"keyNameEnabled\":false,\"keyName\":\"\",\"label\":\"报价截止日期\",\"labelAlign\":\"\",\"type\":\"date\",\"defaultValue\":null,\"placeholder\":\"\",\"columnWidth\":\"200px\",\"size\":\"\",\"autoFullWidth\":true,\"labelWidth\":null,\"labelHidden\":false,\"labelWrap\":false,\"readonly\":false,\"disabled\":false,\"hidden\":false,\"clearable\":true,\"editable\":false,\"format\":\"YYYY-MM-DD\",\"valueFormat\":\"YYYY-MM-DD\",\"required\":false,\"requiredHint\":\"\",\"validation\":\"\",\"validationHint\":\"\",\"customClass\":\"\",\"labelIconClass\":null,\"labelIconPosition\":\"rear\",\"labelTooltip\":null,\"onCreated\":\"\",\"onMounted\":\"\",\"onChange\":\"\",\"onFocus\":\"\",\"onBlur\":\"\",\"onValidate\":\"\"},\"nameReadonly\":true,\"id\":\"date114674\"}],\"options\":{\"name\":\"gridCol109386\",\"hidden\":false,\"span\":12,\"offset\":0,\"push\":0,\"pull\":0,\"responsive\":false,\"md\":12,\"sm\":12,\"xs\":12,\"customClass\":\"\"},\"id\":\"grid-col-109386\"},{\"type\":\"grid-col\",\"category\":\"container\",\"icon\":\"grid-col\",\"internal\":true,\"widgetList\":[{\"type\":\"number\",\"icon\":\"number-field\",\"formItemFlag\":true,\"options\":{\"name\":\"xunjiashichangtian\",\"keyNameEnabled\":false,\"keyName\":\"\",\"label\":\"询价时长/天\",\"labelAlign\":\"\",\"defaultValue\":0,\"placeholder\":\"\",\"columnWidth\":\"200px\",\"size\":\"\",\"controls\":true,\"labelWidth\":null,\"labelHidden\":false,\"labelWrap\":false,\"disabled\":false,\"hidden\":false,\"required\":false,\"requiredHint\":\"\",\"validation\":\"\",\"validationHint\":\"\",\"formulaEnabled\":false,\"formula\":\"\",\"customClass\":\"\",\"labelIconClass\":null,\"labelIconPosition\":\"rear\",\"labelTooltip\":null,\"min\":-100000000000,\"max\":100000000000,\"precision\":0,\"step\":1,\"controlsPosition\":\"right\",\"onCreated\":\"\",\"onMounted\":\"\",\"onChange\":\"\",\"onFocus\":\"\",\"onBlur\":\"\",\"onValidate\":\"\"},\"nameReadonly\":true,\"id\":\"number25336\"}],\"options\":{\"name\":\"gridCol70388\",\"hidden\":false,\"span\":12,\"offset\":0,\"push\":0,\"pull\":0,\"responsive\":false,\"md\":12,\"sm\":12,\"xs\":12,\"customClass\":\"\"},\"id\":\"grid-col-70388\"},{\"type\":\"grid-col\",\"category\":\"container\",\"icon\":\"grid-col\",\"internal\":true,\"widgetList\":[{\"type\":\"input\",\"alias\":\"\",\"icon\":\"text-field\",\"formItemFlag\":true,\"options\":{\"name\":\"xunjiadanbianhao\",\"keyNameEnabled\":false,\"keyName\":\"\",\"label\":\"询价单编号\",\"labelAlign\":\"\",\"type\":\"text\",\"defaultValue\":\"\",\"placeholder\":\"\",\"columnWidth\":\"200px\",\"size\":\"\",\"labelWidth\":null,\"labelHidden\":false,\"labelWrap\":false,\"readonly\":false,\"disabled\":false,\"hidden\":false,\"clearable\":true,\"showPassword\":false,\"required\":false,\"requiredHint\":\"\",\"validation\":\"\",\"validationHint\":\"\",\"customClass\":\"\",\"labelIconClass\":null,\"labelIconPosition\":\"rear\",\"labelTooltip\":null,\"minLength\":null,\"maxLength\":null,\"showWordLimit\":false,\"prefixIcon\":\"\",\"suffixIcon\":\"\",\"appendButton\":false,\"appendButtonDisabled\":false,\"buttonIcon\":\"custom-search\",\"onCreated\":\"\",\"onMounted\":\"\",\"onInput\":\"\",\"onChange\":\"\",\"onFocus\":\"\",\"onBlur\":\"\",\"onValidate\":\"\",\"onAppendButtonClick\":\"\"},\"nameReadonly\":true,\"id\":\"input39231\"}],\"options\":{\"name\":\"gridCol28406\",\"hidden\":false,\"span\":12,\"offset\":0,\"push\":0,\"pull\":0,\"responsive\":false,\"md\":12,\"sm\":12,\"xs\":12,\"customClass\":\"\"},\"id\":\"grid-col-28406\"}],\"options\":{\"name\":\"grid13050\",\"hidden\":false,\"gutter\":12,\"colHeight\":null,\"customClass\":\"\"},\"id\":\"grid13050\"}],\"options\":{\"name\":\"card90304\",\"label\":\"采购发起询价\",\"hidden\":false,\"headerHidden\":false,\"folded\":false,\"showFold\":false,\"cardWidth\":\"100%\",\"shadow\":\"never\",\"customClass\":[]},\"id\":\"card90304\"},{\"key\":90905,\"type\":\"card\",\"category\":\"container\",\"icon\":\"card\",\"widgetList\":[{\"key\":98207,\"type\":\"grid-sub-form\",\"category\":\"container\",\"icon\":\"grid-sub-form\",\"widgetList\":[{\"type\":\"grid\",\"alias\":\"column-4-grid\",\"category\":\"container\",\"icon\":\"column-4-grid\",\"commonFlag\":true,\"cols\":[{\"type\":\"grid-col\",\"category\":\"container\",\"icon\":\"grid-col\",\"internal\":true,\"widgetList\":[{\"type\":\"reference\",\"alias\":\"\",\"icon\":\"reference-field\",\"formItemFlag\":true,\"options\":{\"name\":\"xuanzexuqiu\",\"keyNameEnabled\":false,\"keyName\":\"\",\"label\":\"选择需求\",\"labelAlign\":\"\",\"placeholder\":\"\",\"columnWidth\":\"200px\",\"size\":\"\",\"labelWidth\":null,\"labelHidden\":false,\"labelWrap\":false,\"disabled\":false,\"hidden\":false,\"required\":false,\"requiredHint\":\"\",\"validation\":\"\",\"validationHint\":\"\",\"newTest\":\"\",\"customClass\":[],\"labelIconClass\":null,\"labelIconPosition\":\"rear\",\"labelTooltip\":null,\"prefixIcon\":\"\",\"suffixIcon\":\"\",\"buttonIcon\":\"Search\",\"onCreated\":\"\",\"onMounted\":\"\",\"onChange\":\"\",\"onValidate\":\"\",\"onRecordSelected\":\"\"},\"nameReadonly\":true,\"id\":\"reference39038\"}],\"options\":{\"name\":\"gridCol103434\",\"hidden\":false,\"span\":5,\"offset\":0,\"push\":0,\"pull\":0,\"responsive\":false,\"md\":12,\"sm\":12,\"xs\":12,\"customClass\":\"\"},\"id\":\"grid-col-103434\"},{\"type\":\"grid-col\",\"category\":\"container\",\"icon\":\"grid-col\",\"internal\":true,\"widgetList\":[{\"type\":\"number\",\"icon\":\"number-field\",\"formItemFlag\":true,\"options\":{\"name\":\"lishibaojiyuan\",\"keyNameEnabled\":false,\"keyName\":\"\",\"label\":\"历史报价(含税)/元\",\"labelAlign\":\"\",\"defaultValue\":0,\"placeholder\":\"\",\"columnWidth\":\"200px\",\"size\":\"\",\"controls\":false,\"labelWidth\":null,\"labelHidden\":false,\"labelWrap\":false,\"disabled\":false,\"hidden\":false,\"required\":false,\"requiredHint\":\"\",\"validation\":\"\",\"validationHint\":\"\",\"formulaEnabled\":false,\"formula\":\"\",\"customClass\":[],\"labelIconClass\":null,\"labelIconPosition\":\"rear\",\"labelTooltip\":null,\"min\":-999999999,\"max\":999999999,\"precision\":2,\"step\":1,\"controlsPosition\":\"right\",\"onCreated\":\"\",\"onMounted\":\"\",\"onChange\":\"\",\"onFocus\":\"\",\"onBlur\":\"\",\"onValidate\":\"\"},\"nameReadonly\":true,\"id\":\"number21684\"}],\"options\":{\"name\":\"gridCol41450\",\"hidden\":false,\"span\":4,\"offset\":0,\"push\":0,\"pull\":0,\"responsive\":false,\"md\":12,\"sm\":12,\"xs\":12,\"customClass\":[]},\"id\":\"grid-col-41450\"},{\"type\":\"grid-col\",\"category\":\"container\",\"icon\":\"grid-col\",\"internal\":true,\"widgetList\":[{\"type\":\"number\",\"icon\":\"number-field\",\"formItemFlag\":true,\"options\":{\"name\":\"biaozhuncaigoudanjiyuan\",\"keyNameEnabled\":false,\"keyName\":\"\",\"label\":\"标准采购单价(含税)/元\",\"labelAlign\":\"\",\"defaultValue\":0,\"placeholder\":\"\",\"columnWidth\":\"200px\",\"size\":\"\",\"controls\":false,\"labelWidth\":null,\"labelHidden\":false,\"labelWrap\":false,\"disabled\":false,\"hidden\":false,\"required\":false,\"requiredHint\":\"\",\"validation\":\"\",\"validationHint\":\"\",\"formulaEnabled\":false,\"formula\":\"\",\"customClass\":\"\",\"labelIconClass\":null,\"labelIconPosition\":\"rear\",\"labelTooltip\":null,\"min\":-999999999,\"max\":999999999,\"precision\":2,\"step\":1,\"controlsPosition\":\"right\",\"onCreated\":\"\",\"onMounted\":\"\",\"onChange\":\"\",\"onFocus\":\"\",\"onBlur\":\"\",\"onValidate\":\"\"},\"nameReadonly\":true,\"id\":\"number65314\"}],\"options\":{\"name\":\"gridCol32277\",\"hidden\":false,\"span\":5,\"offset\":0,\"push\":0,\"pull\":0,\"responsive\":false,\"md\":12,\"sm\":12,\"xs\":12,\"customClass\":[]},\"id\":\"grid-col-32277\"},{\"type\":\"grid-col\",\"category\":\"container\",\"icon\":\"grid-col\",\"internal\":true,\"widgetList\":[{\"type\":\"number\",\"icon\":\"number-field\",\"formItemFlag\":true,\"options\":{\"name\":\"baojiadanjianshuiuan\",\"keyNameEnabled\":false,\"keyName\":\"\",\"label\":\"报价单价(含税)/元\",\"labelAlign\":\"\",\"defaultValue\":0,\"placeholder\":\"\",\"columnWidth\":\"200px\",\"size\":\"\",\"controls\":false,\"labelWidth\":null,\"labelHidden\":false,\"labelWrap\":false,\"disabled\":false,\"hidden\":false,\"required\":false,\"requiredHint\":\"\",\"validation\":\"\",\"validationHint\":\"\",\"formulaEnabled\":false,\"formula\":\"\",\"customClass\":[],\"labelIconClass\":null,\"labelIconPosition\":\"rear\",\"labelTooltip\":null,\"min\":-999999999,\"max\":999999999,\"precision\":2,\"step\":1,\"controlsPosition\":\"right\",\"onCreated\":\"\",\"onMounted\":\"\",\"onChange\":\"\",\"onFocus\":\"\",\"onBlur\":\"\",\"onValidate\":\"\"},\"nameReadonly\":true,\"id\":\"number97675\"}],\"options\":{\"name\":\"gridCol4582\",\"hidden\":false,\"span\":5,\"offset\":0,\"push\":0,\"pull\":0,\"responsive\":false,\"md\":12,\"sm\":12,\"xs\":12,\"customClass\":[]},\"id\":\"grid-col-4582\"},{\"type\":\"grid-col\",\"category\":\"container\",\"icon\":\"grid-col\",\"internal\":true,\"widgetList\":[{\"type\":\"number\",\"icon\":\"number-field\",\"formItemFlag\":true,\"options\":{\"name\":\"biaozhunjiazheko\",\"keyNameEnabled\":false,\"keyName\":\"\",\"label\":\"标准价折扣率 %\",\"labelAlign\":\"\",\"defaultValue\":0,\"placeholder\":\"\",\"columnWidth\":\"200px\",\"size\":\"\",\"controls\":false,\"labelWidth\":null,\"labelHidden\":false,\"labelWrap\":false,\"disabled\":false,\"hidden\":false,\"required\":false,\"requiredHint\":\"\",\"validation\":\"\",\"validationHint\":\"\",\"formulaEnabled\":false,\"formula\":\"\",\"customClass\":\"\",\"labelIconClass\":null,\"labelIconPosition\":\"rear\",\"labelTooltip\":null,\"min\":-100000000000,\"max\":100000000000,\"precision\":0,\"step\":1,\"controlsPosition\":\"right\",\"onCreated\":\"\",\"onMounted\":\"\",\"onChange\":\"\",\"onFocus\":\"\",\"onBlur\":\"\",\"onValidate\":\"\"},\"nameReadonly\":true,\"id\":\"number16450\"}],\"options\":{\"name\":\"gridCol47232\",\"hidden\":false,\"span\":5,\"offset\":0,\"push\":0,\"pull\":0,\"responsive\":false,\"md\":12,\"sm\":12,\"xs\":12,\"customClass\":\"\"},\"id\":\"grid-col-47232\"},{\"type\":\"grid-col\",\"category\":\"container\",\"icon\":\"grid-col\",\"internal\":true,\"widgetList\":[{\"type\":\"number\",\"icon\":\"number-field\",\"formItemFlag\":true,\"options\":{\"name\":\"zengzhishuishuil\",\"keyNameEnabled\":false,\"keyName\":\"\",\"label\":\"增值税税率%\",\"labelAlign\":\"\",\"defaultValue\":0,\"placeholder\":\"\",\"columnWidth\":\"200px\",\"size\":\"\",\"controls\":false,\"labelWidth\":null,\"labelHidden\":false,\"labelWrap\":false,\"disabled\":false,\"hidden\":false,\"required\":false,\"requiredHint\":\"\",\"validation\":\"\",\"validationHint\":\"\",\"formulaEnabled\":false,\"formula\":\"\",\"customClass\":\"\",\"labelIconClass\":null,\"labelIconPosition\":\"rear\",\"labelTooltip\":null,\"min\":-100000000000,\"max\":100000000000,\"precision\":0,\"step\":1,\"controlsPosition\":\"right\",\"onCreated\":\"\",\"onMounted\":\"\",\"onChange\":\"\",\"onFocus\":\"\",\"onBlur\":\"\",\"onValidate\":\"\"},\"nameReadonly\":true,\"id\":\"number58655\"}],\"options\":{\"name\":\"gridCol83806\",\"hidden\":false,\"span\":5,\"offset\":0,\"push\":0,\"pull\":0,\"responsive\":false,\"md\":12,\"sm\":12,\"xs\":12,\"customClass\":\"\"},\"id\":\"grid-col-83806\"},{\"type\":\"grid-col\",\"category\":\"container\",\"icon\":\"grid-col\",\"internal\":true,\"widgetList\":[{\"type\":\"number\",\"icon\":\"number-field\",\"formItemFlag\":true,\"options\":{\"name\":\"shuiyuan\",\"keyNameEnabled\":false,\"keyName\":\"\",\"label\":\"税额/元\",\"labelAlign\":\"\",\"defaultValue\":0,\"placeholder\":\"\",\"columnWidth\":\"200px\",\"size\":\"\",\"controls\":false,\"labelWidth\":null,\"labelHidden\":false,\"labelWrap\":false,\"disabled\":false,\"hidden\":false,\"required\":false,\"requiredHint\":\"\",\"validation\":\"\",\"validationHint\":\"\",\"formulaEnabled\":false,\"formula\":\"\",\"customClass\":\"\",\"labelIconClass\":null,\"labelIconPosition\":\"rear\",\"labelTooltip\":null,\"min\":-999999999,\"max\":999999999,\"precision\":2,\"step\":1,\"controlsPosition\":\"right\",\"onCreated\":\"\",\"onMounted\":\"\",\"onChange\":\"\",\"onFocus\":\"\",\"onBlur\":\"\",\"onValidate\":\"\"},\"nameReadonly\":true,\"id\":\"number10635\"}],\"options\":{\"name\":\"gridCol95308\",\"hidden\":false,\"span\":4,\"offset\":0,\"push\":0,\"pull\":0,\"responsive\":false,\"md\":12,\"sm\":12,\"xs\":12,\"customClass\":\"\"},\"id\":\"grid-col-95308\"},{\"type\":\"grid-col\",\"category\":\"container\",\"icon\":\"grid-col\",\"internal\":true,\"widgetList\":[{\"type\":\"input\",\"alias\":\"\",\"icon\":\"text-field\",\"formItemFlag\":true,\"options\":{\"name\":\"baojiazongjin\",\"keyNameEnabled\":false,\"keyName\":\"\",\"label\":\"报价总价(含税)/元\",\"labelAlign\":\"\",\"type\":\"text\",\"defaultValue\":\"\",\"placeholder\":\"\",\"columnWidth\":\"200px\",\"size\":\"\",\"labelWidth\":null,\"labelHidden\":false,\"labelWrap\":false,\"readonly\":false,\"disabled\":false,\"hidden\":false,\"clearable\":true,\"showPassword\":false,\"required\":false,\"requiredHint\":\"\",\"validation\":\"\",\"validationHint\":\"\",\"customClass\":\"\",\"labelIconClass\":null,\"labelIconPosition\":\"rear\",\"labelTooltip\":null,\"minLength\":null,\"maxLength\":null,\"showWordLimit\":false,\"prefixIcon\":\"\",\"suffixIcon\":\"\",\"appendButton\":false,\"appendButtonDisabled\":false,\"buttonIcon\":\"custom-search\",\"onCreated\":\"\",\"onMounted\":\"\",\"onInput\":\"\",\"onChange\":\"\",\"onFocus\":\"\",\"onBlur\":\"\",\"onValidate\":\"\",\"onAppendButtonClick\":\"\"},\"nameReadonly\":true,\"id\":\"input55745\"}],\"options\":{\"name\":\"gridCol79242\",\"hidden\":false,\"span\":5,\"offset\":0,\"push\":0,\"pull\":0,\"responsive\":false,\"md\":12,\"sm\":12,\"xs\":12,\"customClass\":\"\"},\"id\":\"grid-col-79242\"},{\"type\":\"grid-col\",\"category\":\"container\",\"icon\":\"grid-col\",\"internal\":true,\"widgetList\":[{\"type\":\"number\",\"icon\":\"number-field\",\"formItemFlag\":true,\"options\":{\"name\":\"baojiadanjibuhanshan\",\"keyNameEnabled\":false,\"keyName\":\"\",\"label\":\"报价单价(不含税)/元\",\"labelAlign\":\"\",\"defaultValue\":0,\"placeholder\":\"\",\"columnWidth\":\"200px\",\"size\":\"\",\"controls\":false,\"labelWidth\":null,\"labelHidden\":false,\"labelWrap\":false,\"disabled\":false,\"hidden\":false,\"required\":false,\"requiredHint\":\"\",\"validation\":\"\",\"validationHint\":\"\",\"formulaEnabled\":false,\"formula\":\"\",\"customClass\":\"\",\"labelIconClass\":null,\"labelIconPosition\":\"rear\",\"labelTooltip\":null,\"min\":-999999999,\"max\":999999999,\"precision\":2,\"step\":1,\"controlsPosition\":\"right\",\"onCreated\":\"\",\"onMounted\":\"\",\"onChange\":\"\",\"onFocus\":\"\",\"onBlur\":\"\",\"onValidate\":\"\"},\"nameReadonly\":true,\"id\":\"number75313\"}],\"options\":{\"name\":\"gridCol54887\",\"hidden\":false,\"span\":5,\"offset\":0,\"push\":0,\"pull\":0,\"responsive\":false,\"md\":12,\"sm\":12,\"xs\":12,\"customClass\":\"\"},\"id\":\"grid-col-54887\"},{\"type\":\"grid-col\",\"category\":\"container\",\"icon\":\"grid-col\",\"internal\":true,\"widgetList\":[{\"type\":\"number\",\"icon\":\"number-field\",\"formItemFlag\":true,\"options\":{\"name\":\"baojiazongjiabuhanshuiuan\",\"keyNameEnabled\":false,\"keyName\":\"\",\"label\":\"报价总价(不含税)/元\",\"labelAlign\":\"\",\"defaultValue\":0,\"placeholder\":\"\",\"columnWidth\":\"200px\",\"size\":\"\",\"controls\":false,\"labelWidth\":null,\"labelHidden\":false,\"labelWrap\":false,\"disabled\":false,\"hidden\":false,\"required\":false,\"requiredHint\":\"\",\"validation\":\"\",\"validationHint\":\"\",\"formulaEnabled\":false,\"formula\":\"\",\"customClass\":\"\",\"labelIconClass\":null,\"labelIconPosition\":\"rear\",\"labelTooltip\":null,\"min\":-999999999,\"max\":999999999,\"precision\":2,\"step\":1,\"controlsPosition\":\"right\",\"onCreated\":\"\",\"onMounted\":\"\",\"onChange\":\"\",\"onFocus\":\"\",\"onBlur\":\"\",\"onValidate\":\"\"},\"nameReadonly\":true,\"id\":\"number80194\"}],\"options\":{\"name\":\"gridCol80154\",\"hidden\":false,\"span\":5,\"offset\":0,\"push\":0,\"pull\":0,\"responsive\":false,\"md\":12,\"sm\":12,\"xs\":12,\"customClass\":\"\"},\"id\":\"grid-col-80154\"}],\"options\":{\"name\":\"gridsubform52317\",\"hidden\":false,\"gutter\":12,\"colHeight\":null,\"customClass\":[]},\"id\":\"gridsubform52317\"}],\"options\":{\"name\":\"WMSgongyinshangbaojia\",\"label\":\"WMS供应商报价\",\"showBlankRow\":true,\"showRowNumber\":true,\"hidden\":false,\"disabled\":false,\"actionColumnPosition\":\"left\",\"customClass\":\"\",\"onSubFormRowAdd\":\"\",\"onSubFormRowInsert\":\"\",\"onSubFormRowDelete\":\"\",\"onSubFormRowChange\":\"\"},\"id\":\"gridsubform80646\"}],\"options\":{\"name\":\"card26871\",\"label\":\"供应商报价\",\"hidden\":false,\"headerHidden\":false,\"folded\":false,\"showFold\":false,\"cardWidth\":\"100%\",\"shadow\":\"never\",\"customClass\":[]},\"id\":\"card26871\"}],\"formConfig\":{\"modelName\":\"formData\",\"refName\":\"vForm\",\"rulesName\":\"rules\",\"labelWidth\":80,\"labelPosition\":\"top\",\"size\":\"\",\"labelAlign\":\"label-left-align\",\"cssCode\":\"\",\"customClass\":[],\"functions\":\"\",\"layoutType\":\"PC\",\"jsonVersion\":3,\"dataSources\":[],\"onFormCreated\":\"\",\"onFormMounted\":\"\",\"onFormDataChange\":\"\",\"onFormValidate\":\"\"}}",
    "entityLabel": "WMS采购询报价"
}