{
  "detailEntityFlag": false,
  "layoutable": true,
  "internalEntityFlag": false,
  "tags": "ERP(离散制造-MTO）",
  "name": "Shengchangongxu",
  "label": "生产工序",
  "entityCode": 1187,
  "systemEntityFlag": false,
  "listable": true,
  "idFieldName": "shengchangongxuId",
  "mainEntity": null,
  "authorizable": true,
  "assignable": false,
  "nameField": "工序名称",
  "shareable": false,
  "physicalName": "t_shengchangongxu",
  "fieldSet": [
    {
      "name": "shengchangongxuId",
      "idFieldFlag": true,
      "entityCode": 1187,
      "creatable": false,
      "nameFieldFlag": false,
      "mainDetailFieldFlag": false,
      "defaultMemberOfListFlag": false,
      "referTo": null,
      "label": "id主键",
      "physicalName": "shengchangongxuId",
      "type": "PrimaryKey",
      "description": null,
      "displayOrder": 0,
      "fieldId": "0000002-e10833769f164c428b32b5f9e5ba77df",
      "nullable": false,
      "updatable": false,
      "extraAttrs": null,
      "fieldViewModel": {},
      "referenceSetting": null
    },
    {
      "label": "创建时间",
      "updatable": false,
      "defaultMemberOfListFlag": false,
      "extraAttrs": null,
      "fieldId": "0000002-03dd8e2da9ff40948729165e23ede5fb",
      "entityCode": 1187,
      "nullable": false,
      "nameFieldFlag": false,
      "mainDetailFieldFlag": false,
      "referTo": null,
      "referenceSetting": null,
      "physicalName": "createdOn",
      "description": null,
      "type": "DateTime",
      "creatable": false,
      "idFieldFlag": false,
      "fieldViewModel": {},
      "name": "createdOn",
      "displayOrder": 0
    },
    {
      "referenceSetting": null,
      "entityCode": 1187,
      "updatable": false,
      "nameFieldFlag": false,
      "idFieldFlag": false,
      "mainDetailFieldFlag": false,
      "defaultMemberOfListFlag": false,
      "label": "创建用户",
      "physicalName": "createdBy",
      "creatable": false,
      "nullable": false,
      "referTo": "User,",
      "fieldViewModel": {},
      "fieldId": "0000002-32f85724c8e04c42aa2c8150bc5df57d",
      "name": "createdBy",
      "description": null,
      "extraAttrs": null,
      "type": "Reference",
      "displayOrder": 0
    },
    {
      "entityCode": 1187,
      "name": "modifiedOn",
      "description": null,
      "idFieldFlag": false,
      "defaultMemberOfListFlag": false,
      "referenceSetting": null,
      "fieldId": "0000002-99a0ea9708eb40e2985f2d46b216caf7",
      "label": "最近修改时间",
      "type": "DateTime",
      "displayOrder": 0,
      "nullable": true,
      "updatable": false,
      "mainDetailFieldFlag": false,
      "physicalName": "modifiedOn",
      "nameFieldFlag": false,
      "referTo": null,
      "creatable": false,
      "extraAttrs": null,
      "fieldViewModel": {}
    },
    {
      "name": "modifiedBy",
      "label": "修改用户",
      "physicalName": "modifiedBy",
      "displayOrder": 0,
      "nullable": true,
      "mainDetailFieldFlag": false,
      "entityCode": 1187,
      "type": "Reference",
      "creatable": false,
      "idFieldFlag": false,
      "referTo": "User,",
      "fieldId": "0000002-e79856bb324a4d68af1676414410b542",
      "updatable": false,
      "extraAttrs": null,
      "referenceSetting": null,
      "description": null,
      "nameFieldFlag": false,
      "defaultMemberOfListFlag": false,
      "fieldViewModel": {}
    },
    {
      "creatable": false,
      "mainDetailFieldFlag": false,
      "extraAttrs": null,
      "fieldViewModel": {},
      "entityCode": 1187,
      "physicalName": "ownerUser",
      "nullable": false,
      "idFieldFlag": false,
      "defaultMemberOfListFlag": false,
      "referTo": "User,",
      "name": "ownerUser",
      "type": "Reference",
      "displayOrder": 0,
      "referenceSetting": null,
      "description": null,
      "updatable": false,
      "nameFieldFlag": false,
      "fieldId": "0000002-c68ecb6f4b244da7ad52ca652352a885",
      "label": "所属用户"
    },
    {
      "description": null,
      "nameFieldFlag": false,
      "fieldViewModel": {},
      "fieldId": "0000002-0df92b1598ed4781ac53b1d9ac30bd33",
      "physicalName": "ownerDepartment",
      "type": "Reference",
      "creatable": false,
      "mainDetailFieldFlag": false,
      "defaultMemberOfListFlag": false,
      "name": "ownerDepartment",
      "nullable": false,
      "referTo": "Department,",
      "referenceSetting": null,
      "entityCode": 1187,
      "label": "所属部门",
      "updatable": false,
      "displayOrder": 0,
      "idFieldFlag": false,
      "extraAttrs": null
    },
    {
      "referenceSetting": null,
      "entityCode": 1187,
      "nullable": false,
      "creatable": true,
      "updatable": true,
      "extraAttrs": null,
      "name": "gongxubianma",
      "fieldViewModel": {
        "maxLength": 200,
        "validators": [],
        "minLength": 0
      },
      "description": null,
      "displayOrder": 0,
      "nameFieldFlag": false,
      "referTo": null,
      "mainDetailFieldFlag": false,
      "defaultMemberOfListFlag": true,
      "fieldId": "0000002-db67680bf6024803b08e9906c950ba86",
      "label": "工序编码",
      "physicalName": "c_gongxubianma",
      "type": "Text",
      "idFieldFlag": false
    },
    {
      "fieldViewModel": {
        "minLength": 0,
        "maxLength": 200,
        "validators": []
      },
      "fieldId": "0000002-aaf933f0d5a6401d9f80ae76d55c6a2d",
      "physicalName": "c_gongxumingcheng",
      "nullable": false,
      "updatable": true,
      "nameFieldFlag": true,
      "referTo": null,
      "name": "gongxumingcheng",
      "creatable": true,
      "idFieldFlag": false,
      "referenceSetting": null,
      "mainDetailFieldFlag": false,
      "extraAttrs": null,
      "entityCode": 1187,
      "label": "工序名称",
      "type": "Text",
      "description": null,
      "displayOrder": 0,
      "defaultMemberOfListFlag": true
    },
    {
      "name": "gongxujishufujian",
      "description": null,
      "displayOrder": 0,
      "nullable": true,
      "idFieldFlag": false,
      "referenceSetting": null,
      "fieldId": "0000002-949df78dbd4b4d82bc3d1cff4b76f5cd",
      "entityCode": 1187,
      "nameFieldFlag": false,
      "mainDetailFieldFlag": false,
      "type": "File",
      "updatable": true,
      "label": "工序技术附件",
      "physicalName": "c_gongxujishufujian",
      "creatable": true,
      "defaultMemberOfListFlag": false,
      "extraAttrs": null,
      "referTo": null,
      "fieldViewModel": {
        "uploadHint": "",
        "validators": [],
        "maxFileCount": 9,
        "fileMaxSize": 20,
        "uploadFileTypes": []
      }
    },
    {
      "defaultMemberOfListFlag": true,
      "referTo": "Team,",
      "fieldViewModel": {
        "searchDialogWidth": 520,
        "validators": []
      },
      "nullable": true,
      "nameFieldFlag": false,
      "physicalName": "c_shengchanbanzu",
      "description": null,
      "displayOrder": 0,
      "creatable": true,
      "extraAttrs": null,
      "referenceSetting": [
        {
          "filterJson": null,
          "refDetailEntityFlag": null,
          "mainEntityRefFieldOfSelf": null,
          "mainEntityRefFieldOfParent": null,
          "entityName": "Team",
          "fieldList": [
            "teamName",
            "principalId"
          ]
        }
      ],
      "fieldId": "0000002-53f69d7add8a4a0f80a45c47fe952680",
      "entityCode": 1187,
      "label": "生产班组",
      "type": "Reference",
      "name": "shengchanbanzu",
      "updatable": true,
      "idFieldFlag": false,
      "mainDetailFieldFlag": false
    },
    {
      "type": "Reference",
      "displayOrder": 0,
      "nullable": true,
      "nameFieldFlag": false,
      "fieldViewModel": {
        "searchDialogWidth": 520,
        "validators": []
      },
      "entityCode": 1187,
      "description": null,
      "creatable": true,
      "extraAttrs": null,
      "label": "班组长",
      "physicalName": "c_banzuzhang",
      "mainDetailFieldFlag": false,
      "defaultMemberOfListFlag": true,
      "fieldId": "0000002-cf96b3766fb942a4946272f432eff0b3",
      "updatable": true,
      "referTo": "User,",
      "referenceSetting": [
        {
          "mainEntityRefFieldOfParent": null,
          "entityName": "User",
          "fieldList": [
            "userName",
            "departmentId"
          ],
          "filterJson": null,
          "refDetailEntityFlag": null,
          "mainEntityRefFieldOfSelf": null
        }
      ],
      "name": "banzuzhang",
      "idFieldFlag": false
    },
    {
      "entityCode": 1187,
      "label": "班组人数",
      "updatable": true,
      "idFieldFlag": false,
      "nameFieldFlag": false,
      "extraAttrs": null,
      "physicalName": "c_banzurenshu",
      "type": "Integer",
      "creatable": true,
      "fieldViewModel": {
        "validators": [],
        "maxValue": 999999999,
        "minValue": -999999999
      },
      "referenceSetting": null,
      "name": "banzurenshu",
      "nullable": true,
      "mainDetailFieldFlag": false,
      "referTo": null,
      "fieldId": "0000002-ca23c62946284e6c84e5f2b81423ec36",
      "description": null,
      "displayOrder": 0,
      "defaultMemberOfListFlag": true
    },
    {
      "label": "质检员",
      "idFieldFlag": false,
      "defaultMemberOfListFlag": true,
      "fieldViewModel": {
        "searchDialogWidth": 520,
        "validators": []
      },
      "fieldId": "0000002-ab04aaafd9424837bd030da885bc5274",
      "displayOrder": 0,
      "nullable": true,
      "creatable": true,
      "updatable": true,
      "referenceSetting": [
        {
          "refDetailEntityFlag": null,
          "mainEntityRefFieldOfSelf": null,
          "mainEntityRefFieldOfParent": null,
          "entityName": "User",
          "fieldList": [
            "departmentId",
            "userName"
          ],
          "filterJson": null
        }
      ],
      "name": "zhijianyuan",
      "mainDetailFieldFlag": false,
      "extraAttrs": null,
      "referTo": "User,",
      "entityCode": 1187,
      "physicalName": "c_zhijianyuan",
      "type": "Reference",
      "description": null,
      "nameFieldFlag": false
    }
  ]
}